LICENSE
MANIFEST.in
README.rst
containator.conf.example
setup.py
containator/__init__.py
containator/containator.py
containator/defs.py
containator/utils.py
containator/volume.py
containator.egg-info/PKG-INFO
containator.egg-info/SOURCES.txt
containator.egg-info/dependency_links.txt
containator.egg-info/entry_points.txt
containator.egg-info/requires.txt
containator.egg-info/top_level.txt
containator.egg-info/zip-safe