Metadata-Version: 1.1
Name: containator
Version: 0.0.2
Summary: Runs docker containers with pre-defined parameters
Home-page: https://bitbucket.org/beli-sk/containator
Author: Michal Belica
Author-email: devel@beli.sk
License: GPL-3
Keywords: docker,container
Platform: UNKNOWN
Classifier: Development Status :: 3 - Alpha
Classifier: Environment :: Console
Classifier: Intended Audience :: System Administrators
Classifier: License :: OSI Approved :: GNU General Public License v3 or later (GPLv3+)
Classifier: Operating System :: POSIX :: Linux
Classifier: Programming Language :: Python :: 3
